poetry_setuptools_scm_support/__init__.py
poetry_setuptools_scm_support-0.5.9.dist-info/LICENSE
poetry_setuptools_scm_support-0.5.9.dist-info/METADATA
poetry_setuptools_scm_support-0.5.9.dist-info/WHEEL
poetry_setuptools_scm_support-0.5.9.dist-info/entry_points.txt
poetry_setuptools_scm_support-0.5.9.dist-info/RECORD
