Metadata-Version: 2.3
Name: poetry-setuptools-scm-support
Version: 0.5.9
Summary: A Poetry plugin that integrates setuptools-scm 
License: MIT
Keywords: poetry,plugin,setuptools-scm
Author: Luca Stretti
Author-email: laxertu@gmail.com
Requires-Python: >=3.10, <3.13
Classifier: License :: OSI Approved :: MIT License
Classifier: Programming Language :: Python :: 3
Classifier: Programming Language :: Python :: 3.10
Classifier: Programming Language :: Python :: 3.11
Classifier: Programming Language :: Python :: 3.12
Requires-Dist: cleo (>=2.1.0,<3.0.0)
Requires-Dist: poetry (>=2.0.1,<3.0.0)
Requires-Dist: setuptools-scm (>=8.1.0,<9.0.0)
Project-URL: Issues, https://github.com/laxertu/poetry-setuptools-scm-support/issues
Project-URL: Repository, https://github.com/laxertu/poetry-setuptools-scm-support
